{
  "keys": [
    "SHAX-1234-5678-90AB",
    "SHAX-2345-6789-AB1C",
    "SHAX-3456-789A-BC2D",
    "SHAX-4567-89AB-CD3E",
    "SHAX-5678-9ABC-DE4F",
    "SHAX-6789-ABCD-EF5G",
    "SHAX-789A-BCDE-FG6H",
    "SHAX-89AB-CDEF-GH7I",
    "SHAX-9ABC-DEFG-HI8J",
    "SHAX-ABCD-EFGH-IJ9K",
    "SHAX-BCDE-FGHI-JK0L",
    "SHAX-CDEF-GHIJ-KL1M",
    "SHAX-DEFG-HIJK-LM2N",
    "SHAX-EFGH-IJKL-MN3O",
    "SHAX-FGHI-JKLM-NO4P",
    "SHAX-GHIJ-KLMN-OP5Q",
    "SHAX-HIJK-LMNO-PQ6R",
    "SHAX-IJKL-MNOP-QR7S",
    "SHAX-JKLM-NOPQ-RS8T",
    "SHAX-KLMN-OPQR-ST9U",
    "SHAX-LMNO-PQRS-TU0V",
    "SHAX-MNOP-QRST-UV1W",
    "SHAX-NOPQ-RSTU-VW2X",
    "SHAX-OPQR-STUV-WX3Y",
    "SHAX-PQRS-TUVW-XY4Z",
    "SHAX-QRST-UVWX-YZ5A",
    "SHAX-RSTU-VWXY-ZA6B",
    "SHAX-STUV-WXYZ-AB7C",
    "SHAX-TUVW-XYZA-BC8D",
    "SHAX-UVWX-YZAB-CD9E",
    "SHAX-VWXY-ZABC-DE0F",
    "SHAX-WXYZ-ABCD-EF1G",
    "SHAX-XYZ1-BCDE-FG2H",
    "SHAX-YZ12-CDEF-GH3I",
    "SHAX-Z123-DEFG-HI4J",
    "SHAX-1234-EFGH-IJ5K",
    "SHAX-2345-FGHI-JK6L",
    "SHAX-3456-GHIJ-KL7M",
    "SHAX-4567-HIJK-LM8N",
    "SHAX-5678-IJKL-MN9O",
    "SHAX-6789-JKLM-NO0P",
    "SHAX-789A-KLMN-OP1Q",
    "SHAX-89AB-LMNO-PQ2R",
    "SHAX-9ABC-MNOP-QR3S",
    "SHAX-ABCD-NOPQ-RS4T",
    "SHAX-BCDE-OPQR-ST5U",
    "SHAX-CDEF-PQRS-TU6V",
    "SHAX-DEFG-QRST-UV7W",
    "SHAX-EFGH-RSTU-VW8X",
    "SHAX-FGHI-STUV-WX9Y",
    "SHAX-GHIJ-TUVW-XY0Z",
    "SHAX-HIJK-UVWX-YZ1A",
    "SHAX-IJKL-VWXY-ZA2B",
    "SHAX-JKLM-WXYZ-AB3C",
    "SHAX-KLMN-XYZ1-BC4D",
    "SHAX-LMNO-YZ12-CD5E",
    "SHAX-MNOP-Z123-DE6F",
    "SHAX-NOPQ-1234-EF7G",
    "SHAX-OPQR-2345-FG8H",
    "SHAX-PQRS-3456-GH9I",
    "SHAX-QRST-4567-HI0J",
    "SHAX-RSTU-5678-IJ1K",
    "SHAX-STUV-6789-JK2L",
    "SHAX-TUVW-789A-KL3M",
    "SHAX-UVWX-89AB-LM4N",
    "SHAX-VWXY-9ABC-MN5O",
    "SHAX-WXYZ-ABCD-NO6P",
    "SHAX-XYZ1-BCDE-OP7Q",
    "SHAX-YZ12-CDEF-PQ8R",
    "SHAX-Z123-DEFG-QR9S",
    "SHAX-1234-EFGH-RS0T",
    "SHAX-2345-FGHI-ST1U",
    "SHAX-3456-GHIJ-TU2V",
    "SHAX-4567-HIJK-UV3W",
    "SHAX-5678-IJKL-VW4X",
    "SHAX-6789-JKLM-WX5Y",
    "SHAX-789A-KLMN-XY6Z",
    "SHAX-89AB-LMNO-YZ7A",
    "SHAX-9ABC-MNOP-ZA8B",
    "SHAX-ABCD-NOPQ-AB9C",
    "SHAX-BCDE-OPQR-BC0D",
    "SHAX-CDEF-PQRS-CD1E",
    "SHAX-DEFG-QRST-DE2F",
    "SHAX-EFGH-RSTU-EF3G",
    "SHAX-FGHI-STUV-FG4H",
    "SHAX-GHIJ-TUVW-GH5I",
    "SHAX-HIJK-UVWX-HI6J",
    "SHAX-IJKL-VWXY-IJ7K",
    "SHAX-JKLM-WXYZ-JK8L",
    "SHAX-KLMN-XYZ1-KL9M",
    "SHAX-LMNO-YZ12-LM0N",
    "SHAX-MNOP-Z123-MN1O",
    "SHAX-NOPQ-1234-NO2P",
    "SHAX-OPQR-2345-OP3Q",
    "SHAX-PQRS-3456-PQ4R",
    "SHAX-QRST-4567-QR5S",
    "SHAX-RSTU-5678-RS6T",
    "SHAX-STUV-6789-ST7U",
    "SHAX-TUVW-789A-TU8V",
    "SHAX-UVWX-89AB-UV9W",
    "SHAX-VWXY-9ABC-VW0X",
    "SHAX-WXYZ-ABCD-WX1Y",
    "SHAX-XYZ1-BCDE-XY2Z",
    "SHAX-YZ12-CDEF-YZ3A",
    "SHAX-Z123-DEFG-ZA4B"
  ],
  "metadata": {
    "total": 100,
    "last_updated": "2024-01-15",
    "version": "1.0",
    "format": "16-digit license keys"
  }
}
